synriard/__init__.py
synriard/meshes/Alicia_D_v5_6/gripper_100mm/Link1.STL
synriard/meshes/Alicia_D_v5_6/gripper_100mm/Link2.STL
synriard/meshes/Alicia_D_v5_6/gripper_100mm/Link3.STL
synriard/meshes/Alicia_D_v5_6/gripper_100mm/Link4.STL
synriard/meshes/Alicia_D_v5_6/gripper_100mm/Link5.STL
synriard/meshes/Alicia_D_v5_6/gripper_100mm/Link6.STL
synriard/meshes/Alicia_D_v5_6/gripper_100mm/base_link.STL
synriard/meshes/Alicia_D_v5_6/gripper_100mm/girpper_center.STL
synriard/meshes/Alicia_D_v5_6/gripper_100mm/left_gripper.STL
synriard/meshes/Alicia_D_v5_6/gripper_100mm/right_gripper.STL
synriard/meshes/Alicia_D_v5_6/gripper_50mm/Link1.STL
synriard/meshes/Alicia_D_v5_6/gripper_50mm/Link2.STL
synriard/meshes/Alicia_D_v5_6/gripper_50mm/Link3.STL
synriard/meshes/Alicia_D_v5_6/gripper_50mm/Link4.STL
synriard/meshes/Alicia_D_v5_6/gripper_50mm/Link5.STL
synriard/meshes/Alicia_D_v5_6/gripper_50mm/Link6.STL
synriard/meshes/Alicia_D_v5_6/gripper_50mm/base_link.STL
synriard/meshes/Alicia_D_v5_6/gripper_50mm/girpper_center.STL
synriard/meshes/Alicia_D_v5_6/gripper_50mm/left_gripper.STL
synriard/meshes/Alicia_D_v5_6/gripper_50mm/right_gripper.STL
synriard/meshes/Alicia_D_v5_6/leader/base_link.STL
synriard/meshes/Alicia_D_v5_6/leader/link1.STL
synriard/meshes/Alicia_D_v5_6/leader/link2.STL
synriard/meshes/Alicia_D_v5_6/leader/link3.STL
synriard/meshes/Alicia_D_v5_6/leader/link4.STL
synriard/meshes/Alicia_D_v5_6/leader/link5.STL
synriard/meshes/Alicia_D_v5_6/leader/link6.STL
synriard/meshes/Alicia_M_v1_1/base_link.STL
synriard/meshes/Alicia_M_v1_1/grasp_base.STL
synriard/meshes/Alicia_M_v1_1/link1.STL
synriard/meshes/Alicia_M_v1_1/link2.STL
synriard/meshes/Alicia_M_v1_1/link3.STL
synriard/meshes/Alicia_M_v1_1/link4.STL
synriard/meshes/Alicia_M_v1_1/link5.STL
synriard/meshes/Alicia_M_v1_1/link6.STL
synriard/meshes/Alicia_M_v1_1/link7.STL
synriard/meshes/Alicia_M_v1_1/link8.STL
synriard/meshes/Bessica_D_v1_0/withCover/base_link.STL
synriard/meshes/Bessica_D_v1_0/withCover/head.STL
synriard-1.0.2.dist-info/METADATA
synriard-1.0.2.dist-info/WHEEL
synriard-1.0.2.dist-info/top_level.txt
synriard-1.0.2.dist-info/RECORD
