Metadata-Version: 2.4
Name: synriard
Version: 1.0.2
Summary: URDF and MJCF robot description files for Synria robotic platforms.
Author-email: Synria Robotics <support@synriarobotics.ai>
Project-URL: Homepage, https://github.com/Synria-Robotics/Synria-robot-descriptions
Keywords: robotics,urdf,mjcf,robot-description
Classifier: Programming Language :: Python :: 3
Classifier: License :: OSI Approved :: GNU General Public License v3 (GPLv3)
Classifier: Operating System :: OS Independent
Classifier: Topic :: Scientific/Engineering
Requires-Python: >=3.7
Requires-Dist: coacd
Requires-Dist: trimesh
